qrzatca/__init__.py
qrzatca/qr_generator.py
qrzatca-0.1.3.dist-info/LICENSE
qrzatca-0.1.3.dist-info/METADATA
qrzatca-0.1.3.dist-info/WHEEL
qrzatca-0.1.3.dist-info/top_level.txt
qrzatca-0.1.3.dist-info/RECORD
